[
  {
    "id": "undergrad",
    "program": "B.Sc. Double Honours",
    "concentration": "Computer Science, Philosophy",
    "institution": "University of Saskatchewan",
    "institutionLogo" : {
      "image": "usask",
      "alt": "uSask logo",
      "institutionURL": "https://www.usask.ca"
    },
    "startYear": 2017,
    "endYear": 2022,
    "location": "Saskatoon, SK",
    "courseSets": [
      {
        "program": "Computer Science",
        "courseGroups": [
          {
            "status": "complete",
            "courses": [
              {
              "name": "Mathematical Logic and Computing",
              "courseID": "CMPT 260",
              "description": "TODO"
              },
              {
              "name": "Developing Object-Oriented Systems",
              "courseID": "CMPT 270",
              "description": "TODO"
            }, {
              "name": "Programming Principles and Practice",
              "courseID": "CMPT 214",
              "description": "TODO"
            }, {
              "name": "Computer Organization and Architecture",
              "courseID": "CMPT 215",
              "description": "TODO"
            }, {
              "name": "Intermediate Data Structures and Algorithms",
              "courseID": "CMPT 280",
              "description": "TODO"
            }, {
              "name": "Principles of Computer Science",
              "courseID": "CMPT 145",
              "description": "TODO"
            }, {
              "name": "Intro. to Computer Science",
              "courseID": "CMPT 141",
              "description": "TODO"
            }]
          },
          {
            "status": "current",
            "courses": [{
              "name": "Intro. to Artificial Intelligence",
              "courseID": "CMPT 317",
              "description": "TODO"
            }, {
              "name": "Machines and Algorithms",
              "courseID": "CMPT 360",
              "description": "TODO"
            }]
          },
          {
            "status": "planned",
            "courses": [{
              "name": "Formal Languages and Automata",
              "courseID": "CMPT 364",
              "description": "TODO"
            }, {
              "name": "Intermediate Software Engineering",
              "courseID": "CMPT 370",
              "description": "TODO"
            }, {
              "name": "Operating Systems",
              "courseID": "CMPT 332",
              "description": "TODO"
            }, {
              "name": "Information Visualization",
              "courseID": "CMPT 384",
              "description": "TODO"
            }, {
              "name": "Full-Stack Web Programming",
              "courseID": "CMPT 353",
              "description": "TODO"
            }, {
              "name": "Machine Learning",
              "courseID": "CMPT 423",
              "description": "TODO"
            }, {
              "name": "Mobile and Cloud Computing",
              "courseID": "CMPT 436",
              "description": "Was on X"
            }]
          }
        ]
      },
      {
        "program": "PHIL courses",
        "courseGroups": [
          {
            "status": "complete",
            "courses": [{
              "name": "Philosophy of Technology",
              "courseID": "PHIL 236",
              "description": "TODO"
            }, {
              "name": "Metaethics: Morality, Objectivity, and Identity",
              "courseID": "PHIL 333",
              "description": "TODO"
            }, {
              "name": "Ethical Theory",
              "courseID": "PHIL 233",
              "description": "TODO"
            }, {
              "name": "Knowledge, Mind, and Existence",
              "courseID": "PHIL 120",
              "description": "TODO"
            }, {
              "name": "Philosophy of Emotions",
              "courseID": "PHIL 298",
              "description": "TODO"
            }, {
              "name": "Intro. to Ethics and Values",
              "courseID": "PHIL 133",
              "description": "TODO"
            }
            ]
          },
          {
            "status": "current",
            "courses": [{
              "name": "Kantian Ethics",
              "courseID": "PHIL 433",
              "description": "TODO"
            },
              {
                "name": "Social and Political Philosophy",
                "courseID": "PHIL 262",
                "description": "TODO"
              }
            ]
          },
          {
            "status": "planned",
            "courses": [
              {
                "name": "Professional Ethics in CS",
                "courseID": "PHIL 232",
                "description": "TODO"
              },
              {
                "name": "Early Modern Philosophy",
                "courseID": "PHIL 206",
                "description": "TODO"
              },
              {
                "name": "Theory of Knowledge",
                "courseID": "PHIL 285",
                "description": "TODO"
              },
              {
                "name": "Topics in Recent Continental Philosophy",
                "courseID": "PHIL 300+",
                "description": "TODO"
              }
            ]
          }
        ]
      }
    ],

    "detailSection": [
      {
        "sectionTitle": "Undergraduate Info",
        "entry": [
          {
            "entryTitle": "Double-majored in Computer Science and Philosophy in a B.Sc. (with High Honours). Computer Science has given me the theoretical and practical understanding of design, development, and maintenance involved in software development. Majoring in Philosophy has given me an improved understanding of technology, obligation, and ethics, and changed how I develop projects.",
            "points": []
          }
        ]
      },
      {
        "sectionTitle": "Volunteer Experience",
        "entry": [
          {
            "entryTitle": "Arts and Science Students' Union",
            "points": ["Technical Manager", "Sept. 2017 - Present", "Maintained the ASSU's website (Cascade CMS) and general technical support."]
          },
          {
            "entryTitle": "Digitized",
            "points": ["Game Workshop Volunteer", "May 2019"]
          },
          {
            "entryTitle": "Unix Bootcamp Presentation",
            "points": ["Prepared and co-delivered two Intermediate-level Unix bootcamps organized by the Computer Science Students' Society.", "Sept. 2019"]
          }
        ]
      },
      {
        "sectionTitle": "Achievements",
        "entry": [{
          "entryTitle": "ACM Programming Contest",
          "points": ["Local Qualifier Winner (Advanced Category) - Sept. 2019", "Three-person team of myself and fellow classmates won the Advanced level local qualifier at the University for the ACM.", "Placed 23rd of ~70 teams at the Rocky Mountain Regional contest in Edmonton - Oct. 2019"]
        }]
      },
      {
        "sectionTitle": "Groups & Societies",
        "entry": [
          {
            "entryTitle": "Arts and Science Students' Union",
            "points": ["Technical Manager", "Sept. 2017 - Present"]
          },
          {
            "entryTitle": "Computer Science Students' Society",
            "points": ["Member", "Sept. 2017 - Present"]
          },
          {
            "entryTitle": "Cyber Security Team",
            "points": ["Member", "Sept. 2019 - Present"]
          }
        ]
      }
    ]
  },
  {
    "id": "certificate",
    "program": "Certificate of Proficiency",
    "concentration": "Ethics, Justice, Law",
    "institution": "University of Saskatchewan",
    "institutionLogo" : {
      "image": "usask",
      "alt": "uSask logo",
      "institutionURL": "https://www.usask.ca"
    },
    "startYear": 2017,
    "endYear": 2019,
    "location": "Saskatoon, SK",
    "courseSets": [
      {
        "program": "Courses",
        "courseGroups": [
          {
            "status": "complete",
            "courses": [{
              "name": "Introduction to Ethics and Values",
              "courseID": "PHIL 133",
              "description": "TODO"
            }, {
              "name": "Ethical Theory",
              "courseID": "PHIL 233",
              "description": "TODO"
            }, {
              "name": "Philosophy of Technology",
              "courseID": "PHIL 236",
              "description": "TODO"
            }
            ]
          },
          {
            "status": "current",
            "courses": [{
              "name": "Social and Political Philosophy",
              "courseID": "PHIL 262",
              "description": "TODO"
            }
            ]
          }
        ]
      }
    ],
    "detailSection": [
      {
        "sectionTitle": "Certificate Info",
        "entry": [
          {
            "entryTitle": "Provided study in fundamental ethical theory and its application in moral, legal, social, and technological contexts. Completed alongside B.Sc. degree.",
            "points": []
          }
        ]
      }
    ]
  }
]